[{
  "_id": {
    "$oid": "642c78282452ed13a087f5d4"
  },
  "type": "Medic",
  "parent_id": "64259483a587c96f2571262a",
  "status": "pending",
  "qualification": 0,
  "comments": 0,
  "instagram": "rwerwerwerwerwererwe123123",
  "age": 0,
  "years_experience": 0,
  "createdAt": {
    "$numberLong": "1680635944958"
  },
  "updatedAt": {
    "$numberLong": "1681839611675"
  },
  "__v": 0,
  "availables_dates": [],
  "likes": 0
},{
  "_id": {
    "$oid": "643d5b57a089376e6e50a0a3"
  },
  "type": "Medic",
  "parent_id": "64228786353b199547121dfc",
  "status": "pending",
  "qualification": 0,
  "comments": 0,
  "instagram": "https://www.instagram.com/camiloMedina/?hl=es",
  "age": 0,
  "years_experience": 0,
  "createdAt": {
    "$numberLong": "1680635944958"
  },
  "updatedAt": {
    "$numberLong": "1681403769056"
  },
  "__v": 0,
  "availables_dates": [],
  "likes": 0
}]